README.md
setup.py
robowrap/__init__.py
robowrap/arm.py
robowrap/camera.py
robowrap/gun.py
robowrap/helperFuncs.py
robowrap/robowrap.py
robowrap.egg-info/PKG-INFO
robowrap.egg-info/SOURCES.txt
robowrap.egg-info/dependency_links.txt
robowrap.egg-info/requires.txt
robowrap.egg-info/top_level.txt