Metadata-Version: 2.1
Name: robowrap
Version: 0.7.13
Summary: A wrapper for the DJI robomaster library for Python, makes programming the robomaster a little eeasier.
Author: Martin Davies
Author-email: mdavies@kellettschool.com
Classifier: Programming Language :: Python :: 3
Classifier: License :: OSI Approved :: MIT License
Classifier: Operating System :: OS Independent
Requires-Python: >=3.7, <3.9
Requires-Dist: robomaster
Requires-Dist: simple_pid
Requires-Dist: opencv-python==4.2.0.34; platform_system == "Windows"
Requires-Dist: opencv-python; platform_system != "Windows"
